setup.cfg
setup.py
douban_rating/__init__.py
douban_rating/main.py
douban_rating/query.py
douban_rating/rating.py
douban_rating.egg-info/PKG-INFO
douban_rating.egg-info/SOURCES.txt
douban_rating.egg-info/dependency_links.txt
douban_rating.egg-info/entry_points.txt
douban_rating.egg-info/requires.txt
douban_rating.egg-info/top_level.txt