Metadata-Version: 1.0
Name: douban-rating
Version: 0.0.4
Summary: Get douban rating in terminal.
Home-page: https://github.com/Frederick-S/douban-rating
Author: UNKNOWN
Author-email: UNKNOWN
License: UNKNOWN
Platform: UNKNOWN
